bin/upload.py
logie/__init__.py
logie/logutils/__init__.py
logie/logutils/logutils.py
logie/logutils/sourceutils.py
scripts/versioning.py
test/test.py
logie-0.2.0.dist-info/METADATA
logie-0.2.0.dist-info/WHEEL
logie-0.2.0.dist-info/top_level.txt
logie-0.2.0.dist-info/RECORD
